autogen_readme/__init__.py
autogen_readme/__main__.py
autogen_readme/chat_models.py
autogen_readme/cli.py
autogen_readme/custom_arg_types.py
autogen_readme/files.py
autogen_readme/generator.py
autogen_readme/prompts.py
autogen_readme/README.md
autogen_readme-0.0.1.post2.dev0.dist-info/entry_points.txt
autogen_readme-0.0.1.post2.dev0.dist-info/METADATA
autogen_readme-0.0.1.post2.dev0.dist-info/WHEEL
autogen_readme-0.0.1.post2.dev0.dist-info/RECORD
