Metadata-Version: 2.1
Name: autogen-readme
Version: 0.0.1.post2.dev0
Summary: 
Author: wmpons.pro
Author-email: wmpons.pro@gmail.com
Requires-Python: >=3.8.1,<4.0.0
Classifier: Programming Language :: Python :: 3
Classifier: Programming Language :: Python :: 3.9
Classifier: Programming Language :: Python :: 3.10
Classifier: Programming Language :: Python :: 3.11
Classifier: Programming Language :: Python :: 3.12
Requires-Dist: langchain (>=0.2.16,<0.3.0)
Requires-Dist: langchain-core (>=0.2.39,<0.3.0)
Requires-Dist: langchain-openai (>=0.1.24,<0.2.0)
Requires-Dist: typer (>=0.12.5,<0.13.0)
